[
  {
    "py/object": "model.group.Group",
    "footer": "",
    "header": "",
    "id": null,
    "name": ""
  },
  {
    "py/object": "model.group.Group",
    "footer": "footer8wr dTFP8trJB TV",
    "header": "headerhMWx",
    "id": null,
    "name": "name2 D"
  },
  {
    "py/object": "model.group.Group",
    "footer": "footerMsPjGDg1xL ",
    "header": "headershBK7LnHxUf QOFHC m",
    "id": null,
    "name": "nameyrCi"
  },
  {
    "py/object": "model.group.Group",
    "footer": "footervV H4dY6C9",
    "header": "header4Lg57oWF BugH",
    "id": null,
    "name": "name1  "
  },
  {
    "py/object": "model.group.Group",
    "footer": "footerGCZF",
    "header": "headerMLbI",
    "id": null,
    "name": "nameAWO Wbn"
  },
  {
    "py/object": "model.group.Group",
    "footer": "footer",
    "header": "headerVgb Y  ",
    "id": null,
    "name": "name y"
  }
]